AUTHORS
LICENSE
MANIFEST.in
README.rst
VERSION.txt
setup.py
urbanairship/__about__.py
urbanairship/__init__.py
urbanairship/common.py
urbanairship/core.py
urbanairship/devices/__init__.py
urbanairship/devices/devicelist.py
urbanairship/push/__init__.py
urbanairship/push/audience.py
urbanairship/push/core.py
urbanairship/push/payload.py
urbanairship/push/schedule.py
urbanairship/tests/__init__.py
urbanairship/tests/push/__init__.py
urbanairship/tests/push/test_audience.py
urbanairship/tests/push/test_message.py
urbanairship/tests/push/test_push.py
urbanairship/tests/push/test_schedule.py
urbanairship3.egg-info/PKG-INFO
urbanairship3.egg-info/SOURCES.txt
urbanairship3.egg-info/dependency_links.txt
urbanairship3.egg-info/requires.txt
urbanairship3.egg-info/top_level.txt