Metadata-Version: 1.1
Name: urbanairship3
Version: 0.6.3
Summary: Python package for using the Urban Airship API
Home-page: http://urbanairship.com/
Author: Adam Lowry
Author-email: adam@urbanairship.com
License: BSD License
Platform: UNKNOWN
Classifier: Programming Language :: Python :: 2
Classifier: Programming Language :: Python :: 3
Classifier: Development Status :: 4 - Beta
Classifier: Environment :: Web Environment
Classifier: Intended Audience :: Developers
Classifier: License :: OSI Approved :: Apache Software License
Classifier: Operating System :: OS Independent
Classifier: Topic :: Software Development :: Libraries
